cpu/modules/registers.sv
// vim: set ft=systemverilog:

// registers has 4 general registers to read/write
// and be able to read 2 registers simultaneously
// to write 1 register at once
module registers #(
    parameter N = 32, // N is bit width of registers
    parameter M = 2  // 2^M numbers of registers
)(
    input clk, // clock
    input rst, // reset
    input [M-1:0] r1,  // register id 1 to read
    input [M-1:0] r2,  // register id 2 to read
    input [M:0] w1,  // register id to write if MSB is 1 this is disabled
    input [N-1:0] w,  // value to write
    output reg [N-1:0] v1, // register 1 value to read
    output reg [N-1:0] v2 // register 2 value to read
);
    reg [N-1:0] regs[2**M-1:0]; // internal registers (4 items)
    integer i;

    always @(posedge clk or negedge rst) begin
        if (!rst) begin
            for (i = 0; i < 2**M; i++) begin
                regs[i] = 0;
            end
        end

        if (w1[M] == 0) begin
            regs[w1] = w;
        end

        v1 = regs[r1];
        v2 = regs[r2];
    end
endmodule

cpu/testbenches/registers_test.sv
// vim: set ft=systemverilog:

`timescale 1ns/100ps
module test_registers();
    parameter N=32;

    reg clk;
    reg rst;
    reg [1:0] r1;
    reg [1:0] r2;
    reg [2:0] w1;
    reg [N-1:0] w;
    wire [N-1:0] v1;
    wire [N-1:0] v2;

    registers regs(
        .clk(clk),
        .rst(rst),
        .r1(r1),
        .r2(r2),
        .w1(w1),
        .w(w),
        .v1(v1),
        .v2(v2));

    always #5
        clk <= !clk;

    initial begin
        $dumpfile("registers_test.vcd");
        $dumpvars(0, test_registers);

        #1 rst = 0; clk = 0; r1 = 0; r2 = 0; w1 = 0; w = 0;
        #10 rst = 1;
        #10 w1 = 0; w = 32'd01;
        #10 w1 = 1; w = 32'b11;
        #10 w1 = 2; w = 32'b111;
        #10 w1 = 3; w = 32'hffffffff;
        #10 w1 = 4;
        #10 r1 = 0; r2 = 1;
        #10 r1 = 2; r2 = 3;
        #10 w1 = 3; w = 0;
        #10 w1 = 4; w = 32'd100;
        #10 $finish;
    end
endmodule

cpu/register_test.vcd
$date
	Fri Jan 24 18:17:42 2020
$end
$version
	Icarus Verilog
$end
$timescale
	100ps
$end
$scope module test_registers $end
$var wire 32 ! v2 [31:0] $end
$var wire 32 " v1 [31:0] $end
$var reg 1 # clk $end
$var reg 2 $ r1 [1:0] $end
$var reg 2 % r2 [1:0] $end
$var reg 1 & rst $end
$var reg 32 ' w [31:0] $end
$var reg 3 ( w1 [2:0] $end
$scope module regs $end
$var wire 1 # clk $end
$var wire 2 ) r1 [1:0] $end
$var wire 2 * r2 [1:0] $end
$var wire 1 & rst $end
$var wire 32 + w [31:0] $end
$var wire 3 , w1 [2:0] $end
$var reg 32 - v1 [31:0] $end
$var reg 32 . v2 [31:0] $end
$var integer 32 / i [31:0] $end
$upscope $end
$upscope $end
$enddefinitions $end
#0
$dumpvars
bx /
bx .
bx -
bx ,
bx +
bx *
bx )
bx (
bx '
x&
bx %
bx $
x#
bx "
bx !
$end
#10
b0 !
b0 .
b0 "
b0 -
b100 /
b0 '
b0 +
b0 (
b0 ,
b0 %
b0 *
b0 $
b0 )
0#
0&
#50
b100 /
1#
#100
0#
#110
1&
#150
1#
#200
0#
#210
b1 '
b1 +
#250
b1 !
b1 .
b1 "
b1 -
1#
#300
0#
#310
b11 '
b11 +
b1 (
b1 ,
#350
1#
#400
0#
#410
b111 '
b111 +
b10 (
b10 ,
#450
1#
#500
0#
#510
b11111111111111111111111111111111 '
b11111111111111111111111111111111 +
b11 (
b11 ,
#550
1#
#600
0#
#610
b100 (
b100 ,
#650
1#
#700
0#
#710
b1 %
b1 *
#750
b11 !
b11 .
1#
#800
0#
#810
b11 %
b11 *
b10 $
b10 )
#850
b11111111111111111111111111111111 !
b11111111111111111111111111111111 .
b111 "
b111 -
1#
#900
0#
#910
b0 '
b0 +
b11 (
b11 ,
#950
b0 !
b0 .
1#
#1000
0#
#1010
b1100100 '
b1100100 +
b100 (
b100 ,
